<!--
CMS result for mu(ttH, 1l 2tau) at mH = 125 GeV
http://cms-results.web.cern.ch/cms-results/public-results/publications/HIG-17-018/
-->

<expmu dim="1" type="n">
  <experiment>CMS</experiment>
  <source type="published">HIG-17-018</source>
  <sqrts>13</sqrts>
  <mass>125</mass>

  <eff prod="ttH" decay="WW">0.038</eff>
  <eff prod="ttH" decay="tautau">0.954</eff>
  <eff prod="ttH" decay="ZZ">0.008</eff>

  <bestfit>-1.52</bestfit>
  
  <param>
    <uncertainty side="left">-1.72</uncertainty>
    <uncertainty side="right">1.76</uncertainty>
    <!-- if not needed, just <uncertainty></uncertainty> -->
  </param>
</expmu>
